logical_gates/__init__.py
logical_gates/logic.py
logical_gates-1.0.dist-info/METADATA
logical_gates-1.0.dist-info/WHEEL
logical_gates-1.0.dist-info/top_level.txt
logical_gates-1.0.dist-info/RECORD
