Metadata-Version: 2.1
Name: logical-gates
Version: 1.0
Summary: A library to use advanced logic gates.
Home-page: UNKNOWN
Author: LesCodeursProLFJM
License: MIT
Platform: UNKNOWN
